LICENSE.txt
README.md
setup.py
cmfd/__init__.py
cmfd/utils.py
cmfd.egg-info/PKG-INFO
cmfd.egg-info/SOURCES.txt
cmfd.egg-info/dependency_links.txt
cmfd.egg-info/top_level.txt