Metadata-Version: 2.1
Name: cmfd
Version: 0.2.1
Summary: Chinese Moral Foundation Dictionary 2.0
Home-page: https://github.com/civictechlab/cmfd
Author: zhiyuan liu
Author-email: zyliumedia@gmail.com
License: MIT
Classifier: License :: OSI Approved :: MIT License
Classifier: Programming Language :: Python
Classifier: Programming Language :: Python :: 3
Classifier: Programming Language :: Python :: 3.6
Classifier: Programming Language :: Python :: Implementation :: CPython
Classifier: Programming Language :: Python :: Implementation :: PyPy
Requires-Python: >=3.6.0
License-File: LICENSE.txt
